Q_Learning_O_Run/Q_learning.py
Q_Learning_O_Run/__init__.py
Q_Learning_O_Run/env.py
Q_Learning_O_Run-0.0.2.dist-info/LICENSE
Q_Learning_O_Run-0.0.2.dist-info/METADATA
Q_Learning_O_Run-0.0.2.dist-info/WHEEL
Q_Learning_O_Run-0.0.2.dist-info/top_level.txt
Q_Learning_O_Run-0.0.2.dist-info/RECORD
