Metadata-Version: 2.1
Name: Q-Learning-O-Run
Version: 0.0.2
Summary: 用于Q-learning的学习,内含MDP环境和Q-learning决策大脑
Home-page: https://github.com/353055619/Q_Learning_O_Run.git
Author: Godw
Author-email: 353055619@qq.com
License: UNKNOWN
Platform: UNKNOWN
Classifier: Programming Language :: Python :: 3
Classifier: License :: OSI Approved :: MIT License
Classifier: Operating System :: OS Independent
Requires-Python: >=3.6
License-File: LICENSE
